navarp/__init__.py
navarp/navarp_gui.py
navarp/extras/__init__.py
navarp/extras/simulation.py
navarp/gui/about.ui
navarp/gui/export.ui
navarp/gui/main.ui
navarp/gui/icons/navarp.svg
navarp/utils/__init__.py
navarp/utils/fermilevel.py
navarp/utils/isocut.py
navarp/utils/isomclass.py
navarp/utils/kinterp.py
navarp/utils/ktransf.py
navarp/utils/navfile.py
navarp/utils/navplt.py
navarp-1.6.0.dist-info/AUTHORS.rst
navarp-1.6.0.dist-info/LICENSE
navarp-1.6.0.dist-info/METADATA
navarp-1.6.0.dist-info/WHEEL
navarp-1.6.0.dist-info/entry_points.txt
navarp-1.6.0.dist-info/top_level.txt
navarp-1.6.0.dist-info/RECORD
