Metadata-Version: 2.1
Name: navarp
Version: 1.6.0
Summary: Navigation tool for ARPES data.
Home-page: https://gitlab.com/fbisti/navarp
Author: Federico Bisti
Author-email: federico.bisti@univaq.it
License: GPLv3+
Keywords: navarp
Classifier: Development Status :: 4 - Beta
Classifier: Intended Audience :: Science/Research
Classifier: Intended Audience :: Developers
Classifier: License :: OSI Approved :: GNU General Public License v3 or later (GPLv3+)
Classifier: Natural Language :: English
Classifier: Operating System :: MacOS
Classifier: Operating System :: Microsoft :: Windows
Classifier: Operating System :: POSIX :: Linux
Classifier: Programming Language :: Python :: 3
Classifier: Programming Language :: Python :: 3.5
Classifier: Programming Language :: Python :: 3.6
Classifier: Programming Language :: Python :: 3.7
Classifier: Programming Language :: Python :: 3.8
Classifier: Topic :: Scientific/Engineering :: Physics
Requires-Python: >=3.5.0
License-File: LICENSE
License-File: AUTHORS.rst
Requires-Dist: numpy (>=1.16.0)
Requires-Dist: scipy (>=1.3.0)
Requires-Dist: matplotlib (>=3.5.2)
Requires-Dist: h5py (>=2.9.0)
Requires-Dist: pyyaml
Requires-Dist: igor2
Requires-Dist: colorcet
Requires-Dist: Click
